rhqmenu/__init__.py
rhqmenu/menu.py
rhq_menu-1.0.0.dist-info/METADATA
rhq_menu-1.0.0.dist-info/WHEEL
rhq_menu-1.0.0.dist-info/top_level.txt
rhq_menu-1.0.0.dist-info/RECORD
