Metadata-Version: 2.1
Name: rhq-menu
Version: 1.0.0
Summary: A Modular, Extensible and Highly Scalable Menu Framework.
Home-page: https://rhq.pw/
Author: RHQ-Rusty
Author-email: rusty@rhq.pw
License: UNKNOWN
Platform: UNKNOWN
Classifier: Programming Language :: Python :: 3
Classifier: License :: OSI Approved :: MIT License
Classifier: Operating System :: OS Independent
Requires-Python: >=3.6
